frstool/__init__.py
frstool/apiclient.py
frstool-1.0.3.dist-info/METADATA
frstool-1.0.3.dist-info/WHEEL
frstool-1.0.3.dist-info/top_level.txt
frstool-1.0.3.dist-info/RECORD
