Metadata-Version: 2.1
Name: frstool
Version: 1.0.3
Summary: Financial Resilience Score Tool Solution
Home-page: https://financialresiliencescore.com
Author: 5sigma
Author-email: Anton Shishkin <ashishkin@5sigma.co>
Project-URL: Homepage, https://financialresiliencescore.com
Project-URL: Issues, https://financialresiliencescore.com
Classifier: Programming Language :: Python :: 3.12
Classifier: License :: OSI Approved :: GNU General Public License (GPL)
Classifier: Operating System :: OS Independent
Requires-Python: >=3.12
Requires-Dist: requests>=2.32.3
